[{"id":{"id":"bn:00000288n","pos":"NOUN","source":"BABELNET"},"bKeyConcept":false,"bLoaded":true,"senses":[{"fullLemma":"일탈_행동","simpleLemma":"일탈_행동","source":"WIKI","senseKey":"857990","frequency":0,"language":"KO","pos":"NOUN","synsetID":{"id":"bn:00000288n","pos":"NOUN","source":"BABELNET"},"translationInfo":"","pronunciations":{"audios":[],"transcriptions":[]},"bKeySense":false,"idSense":46507783},{"fullLemma":"일탈_행동","simpleLemma":"일탈_행동","source":"WIKIDATA","senseKey":"Q623184","frequency":0,"language":"KO","pos":"NOUN","synsetID":{"id":"bn:00000288n","pos":"NOUN","source":"BABELNET"},"translationInfo":"","pronunciations":{"audios":[],"transcriptions":[]},"bKeySense":false,"idSense":213748588},{"fullLemma":"aberrance","simpleLemma":"aberrance","source":"WNTR","senseKey":"","frequency":0,"language":"KO","pos":"NOUN","synsetID":{"id":"bn:00000288n","pos":"NOUN","source":"BABELNET"},"translationInfo":"1.0_0_0","pronunciations":{"audios":[],"transcriptions":[]},"bKeySense":false,"idSense":46507701},{"fullLemma":"aberrancy","simpleLemma":"aberrancy","source":"WNTR","senseKey":"","frequency":0,"language":"KO","pos":"NOUN","synsetID":{"id":"bn:00000288n","pos":"NOUN","source":"BABELNET"},"translationInfo":"1.0_0_0","pronunciations":{"audios":[],"transcriptions":[]},"bKeySense":false,"idSense":46507651}],"domains":{"HEALTH_AND_MEDICINE":-1.0,"PHILOSOPHY_AND_PSYCHOLOGY":0.4907324016094208},"lnToCompound":{},"lnToOtherForm":{},"wnOffsets":[{"versionMapping":{"1.6":["10404925n"],"3.0":["14503665n"],"2.1":["14311051n"],"2.0":["13677823n"],"1.7":["12247365n"],"1.5":["08757215n"]},"version":"WN_30","id":"wn:14503665n","pos":"NOUN","source":"WN"}],"mainSenses":{},"glosses":[{"source":"WN","sourceSense":"46507627","language":"EN","gloss":"A state or condition markedly different from the norm","tokens":[{"start":2,"end":6,"id":{"id":"bn:00074009n","pos":"NOUN","source":"BABELNET"},"word":"state"},{"start":21,"end":28,"id":{"id":"bn:00116197r","pos":"ADV","source":"BABELNET"},"word":"markedly"},{"start":49,"end":52,"id":{"id":"bn:00058008n","pos":"NOUN","source":"BABELNET"},"word":"norm"}]},{"source":"WIKI","sourceSense":"46507767","language":"EN","gloss":"In sociology, deviance describes an action or behavior that violates social norms, including a formally enacted rule, as well as informal violations of social norms.","tokens":[{"start":152,"end":163,"id":{"id":"bn:03189203n","pos":"NOUN","source":"BABELNET"},"word":"social norms"},{"start":3,"end":11,"id":{"id":"bn:00072574n","pos":"NOUN","source":"BABELNET"},"word":"sociology"},{"start":46,"end":53,"id":{"id":"bn:00009657n","pos":"NOUN","source":"BABELNET"},"word":"behavior"},{"start":69,"end":80,"id":{"id":"bn:03189203n","pos":"NOUN","source":"BABELNET"},"word":"social norms"}]},{"source":"WIKIDIS","sourceSense":"46507767","language":"EN","gloss":"Actions or behaviors that violate social norms","tokens":[{"start":41,"end":45,"id":{"id":"bn:00058008n","pos":"NOUN","source":"BABELNET"},"word":"norms"},{"start":11,"end":19,"id":{"id":"bn:00009657n","pos":"NOUN","source":"BABELNET"},"word":"behaviors"},{"start":34,"end":45,"id":{"id":"bn:03189203n","pos":"NOUN","source":"BABELNET"},"word":"social norms"}]},{"source":"OMWIKI","sourceSense":"46507742","language":"EN","gloss":"A state or condition markedly different from the norm.","tokens":[]},{"source":"WIKT","sourceSense":"46508010","language":"EN","gloss":"Actions or behaviors that violate formal and informal cultural norms such as laws and customs.","tokens":[]},{"source":"WIKTLB","sourceSense":"46508010","language":"EN","gloss":"Person or thing that differs from the expected.","tokens":[]},{"source":"WIKI","sourceSense":"46507783","language":"KO","gloss":"일탈 행동이란 사회에서 규정한 제도나 규범에서 벗어난 행위를 말한다.","tokens":[]}],"examples":[],"images":[{"name":"SNA_segment.png#WIKI","languages":["FI","JA","FA","ZH","VI","CA"],"urlSource":"WIKI","license":"CC_BY_SA_30","thumbUrl":"https://upload.wikimedia.org/wikipedia/commons/thumb/c/c7/SNA_segment.png/200px-SNA_segment.png","url":"https://upload.wikimedia.org/wikipedia/commons/c/c7/SNA_segment.png","badImage":false},{"name":"Pentonvilleiso19.jpg#WIKI","languages":["UK","JA","FA","EN"],"urlSource":"WIKI","license":"CC_BY_SA_30","thumbUrl":"https://upload.wikimedia.org/wikipedia/commons/thumb/6/6e/Pentonvilleiso19.jpg/200px-Pentonvilleiso19.jpg","url":"https://upload.wikimedia.org/wikipedia/commons/6/6e/Pentonvilleiso19.jpg","badImage":false},{"name":"Social_Network_Diagram_(segment).svg#WIKI","languages":["SR","PT","EN"],"urlSource":"WIKI","license":"CC_BY_SA_30","thumbUrl":"https://upload.wikimedia.org/wikipedia/commons/e/e4/Social_Network_Diagram_%28segment%29.svg","url":"https://upload.wikimedia.org/wikipedia/commons/e/e4/Social_Network_Diagram_%28segment%29.svg","badImage":false},{"name":"Non-smoking.JPG#WIKI","languages":["PL","ES","NL"],"urlSource":"WIKI","license":"CC_BY_SA_30","thumbUrl":"https://upload.wikimedia.org/wikipedia/commons/thumb/2/27/Non-smoking.JPG/200px-Non-smoking.JPG","url":"https://upload.wikimedia.org/wikipedia/commons/2/27/Non-smoking.JPG","badImage":false},{"name":"Mertons_social_strain_theory.svg#WIKI","languages":["NL","EN"],"urlSource":"WIKI","license":"CC_BY_SA_30","thumbUrl":"https://upload.wikimedia.org/wikipedia/commons/3/38/Mertons_social_strain_theory.svg","url":"https://upload.wikimedia.org/wikipedia/commons/3/38/Mertons_social_strain_theory.svg","badImage":false},{"name":"Normas.JPG#WIKI","languages":["PT","ES"],"urlSource":"WIKI","license":"CC_BY_SA_30","thumbUrl":"https://upload.wikimedia.org/wikipedia/commons/thumb/3/3a/Normas.JPG/200px-Normas.JPG","url":"https://upload.wikimedia.org/wikipedia/commons/3/3a/Normas.JPG","badImage":false},{"name":"Ciencias_sociais.svg#WIKI","languages":["JA"],"urlSource":"WIKI","license":"CC_BY_SA_30","thumbUrl":"https://upload.wikimedia.org/wikipedia/commons/4/4c/Ciencias_sociais.svg","url":"https://upload.wikimedia.org/wikipedia/commons/4/4c/Ciencias_sociais.svg","badImage":false},{"name":"JPATS-prisoners_stepping_down_an_aircraft.jpg#WIKI","languages":["VI"],"urlSource":"WIKI","license":"CC_BY_SA_30","thumbUrl":"https://upload.wikimedia.org/wikipedia/commons/thumb/a/a7/JPATS-prisoners_stepping_down_an_aircraft.jpg/200px-JPATS-prisoners_stepping_down_an_aircraft.jpg","url":"https://upload.wikimedia.org/wikipedia/commons/a/a7/JPATS-prisoners_stepping_down_an_aircraft.jpg","badImage":false},{"name":"Socio.svg#WIKI","languages":["PT"],"urlSource":"WIKI","license":"CC_BY_SA_30","thumbUrl":"https://upload.wikimedia.org/wikipedia/commons/2/2e/Socio.svg","url":"https://upload.wikimedia.org/wikipedia/commons/2/2e/Socio.svg","badImage":false},{"name":"The_Cure-Live-2005.jpg#WIKI","languages":["VI"],"urlSource":"WIKI","license":"CC_BY_SA_30","thumbUrl":"https://upload.wikimedia.org/wikipedia/commons/thumb/2/2f/The_Cure-Live-2005.jpg/200px-The_Cure-Live-2005.jpg","url":"https://upload.wikimedia.org/wikipedia/commons/2/2f/The_Cure-Live-2005.jpg","badImage":false},{"name":"Psi2.png#WIKI","languages":["IT"],"urlSource":"WIKI","license":"CC_BY_SA_30","thumbUrl":"https://upload.wikimedia.org/wikipedia/commons/thumb/e/e1/Psi2.png/200px-Psi2.png","url":"https://upload.wikimedia.org/wikipedia/commons/e/e1/Psi2.png","badImage":false},{"name":"Blue_question_mark.svg#WIKI","languages":["RO"],"urlSource":"WIKI","license":"CC_BY_SA_30","thumbUrl":"https://upload.wikimedia.org/wikipedia/commons/b/b2/Blue_question_mark.svg","url":"https://upload.wikimedia.org/wikipedia/commons/b/b2/Blue_question_mark.svg","badImage":false},{"name":"Surveillance_cameras.jpg#WIKI","languages":["ES"],"urlSource":"WIKI","license":"CC_BY_SA_30","thumbUrl":"https://upload.wikimedia.org/wikipedia/commons/thumb/0/0c/Surveillance_cameras.jpg/200px-Surveillance_cameras.jpg","url":"https://upload.wikimedia.org/wikipedia/commons/0/0c/Surveillance_cameras.jpg","badImage":false},{"name":"Social_sciences.svg#WIKI","languages":["FR"],"urlSource":"WIKI","license":"CC_BY_SA_30","thumbUrl":"https://upload.wikimedia.org/wikipedia/commons/4/42/Social_sciences.svg","url":"https://upload.wikimedia.org/wikipedia/commons/4/42/Social_sciences.svg","badImage":false},{"name":"Korrektúra.png#WIKI","languages":["HU"],"urlSource":"WIKI","license":"OTHER","thumbUrl":"https://upload.wikimedia.org/wikipedia/hu/thumb/9/98/Korrekt%C3%BAra.png/200px-Korrekt%C3%BAra.png","url":"https://upload.wikimedia.org/wikipedia/hu/9/98/Korrekt%C3%BAra.png","badImage":false},{"name":"Ffm-obdachloser.jpg#WIKI","languages":["VI"],"urlSource":"WIKI","license":"CC_BY_SA_30","thumbUrl":"https://upload.wikimedia.org/wikipedia/commons/thumb/a/a2/Ffm-obdachloser.jpg/200px-Ffm-obdachloser.jpg","url":"https://upload.wikimedia.org/wikipedia/commons/a/a2/Ffm-obdachloser.jpg","badImage":false},{"name":"Criminal_brains.jpg#WIKI","languages":["NL"],"urlSource":"WIKI","license":"CC_BY_SA_30","thumbUrl":"https://upload.wikimedia.org/wikipedia/commons/thumb/b/b0/Criminal_brains.jpg/200px-Criminal_brains.jpg","url":"https://upload.wikimedia.org/wikipedia/commons/b/b0/Criminal_brains.jpg","badImage":false},{"name":"Martin_Van_Maele_-_La_Grande_Danse_macabre_des_vifs_-_02.jpg#WIKI","languages":["ES"],"urlSource":"WIKI","license":"CC_BY_SA_30","thumbUrl":"https://upload.wikimedia.org/wikipedia/commons/thumb/d/d8/Martin_Van_Maele_-_La_Grande_Danse_macabre_des_vifs_-_02.jpg/200px-Martin_Van_Maele_-_La_Grande_Danse_macabre_des_vifs_-_02.jpg","url":"https://upload.wikimedia.org/wikipedia/commons/d/d8/Martin_Van_Maele_-_La_Grande_Danse_macabre_des_vifs_-_02.jpg","badImage":false},{"name":"Crystal_Clear_app_Community_Help.png#WIKI","languages":["UK"],"urlSource":"WIKI","license":"CC_BY_SA_30","thumbUrl":"https://upload.wikimedia.org/wikipedia/commons/6/64/Crystal_Clear_app_Community_Help.png","url":"https://upload.wikimedia.org/wikipedia/commons/6/64/Crystal_Clear_app_Community_Help.png","badImage":false},{"name":"P_Society.png#WIKI","languages":["AR"],"urlSource":"WIKI","license":"CC_BY_SA_30","thumbUrl":"https://upload.wikimedia.org/wikipedia/commons/c/ce/P_Society.png","url":"https://upload.wikimedia.org/wikipedia/commons/c/ce/P_Society.png","badImage":false},{"name":"Merton.jpg#WIKI","languages":["PL"],"urlSource":"WIKI","license":"CC_BY_SA_30","thumbUrl":"https://upload.wikimedia.org/wikipedia/commons/thumb/c/c0/Merton.jpg/200px-Merton.jpg","url":"https://upload.wikimedia.org/wikipedia/commons/c/c0/Merton.jpg","badImage":false},{"name":"Emile_Durkheim.jpg#WIKI","languages":["ES"],"urlSource":"WIKI","license":"CC_BY_SA_30","thumbUrl":"https://upload.wikimedia.org/wikipedia/commons/thumb/2/24/Emile_Durkheim.jpg/200px-Emile_Durkheim.jpg","url":"https://upload.wikimedia.org/wikipedia/commons/2/24/Emile_Durkheim.jpg","badImage":false},{"name":"Logo_sociology.svg#WIKI","languages":["ES"],"urlSource":"WIKI","license":"CC_BY_SA_30","thumbUrl":"https://upload.wikimedia.org/wikipedia/commons/a/a6/Logo_sociology.svg","url":"https://upload.wikimedia.org/wikipedia/commons/a/a6/Logo_sociology.svg","badImage":false},{"name":"People.svg#WIKI","languages":["IT"],"urlSource":"WIKI","license":"CC_BY_SA_30","thumbUrl":"https://upload.wikimedia.org/wikipedia/commons/0/0f/People.svg","url":"https://upload.wikimedia.org/wikipedia/commons/0/0f/People.svg","badImage":false},{"name":"P_anthropology.png#WIKI","languages":["PT"],"urlSource":"WIKI","license":"CC_BY_SA_30","thumbUrl":"https://upload.wikimedia.org/wikipedia/commons/1/19/P_anthropology.png","url":"https://upload.wikimedia.org/wikipedia/commons/1/19/P_anthropology.png","badImage":false},{"name":"Kent_State_massacre.jpg#WIKI","languages":["VI"],"urlSource":"WIKI","license":"OTHER","thumbUrl":"https://upload.wikimedia.org/wikipedia/en/thumb/6/65/Kent_State_massacre.jpg/200px-Kent_State_massacre.jpg","url":"https://upload.wikimedia.org/wikipedia/en/6/65/Kent_State_massacre.jpg","badImage":false},{"name":"Death_Penalty_World_Map.svg#WIKI","languages":["ES"],"urlSource":"WIKI","license":"CC_BY_SA_30","thumbUrl":"https://upload.wikimedia.org/wikipedia/commons/8/80/Death_Penalty_World_Map.svg","url":"https://upload.wikimedia.org/wikipedia/commons/8/80/Death_Penalty_World_Map.svg","badImage":false},{"name":"Eintracht_hooligans.jpg#WIKI","languages":["NL"],"urlSource":"WIKI","license":"CC_BY_SA_30","thumbUrl":"https://upload.wikimedia.org/wikipedia/commons/thumb/6/6c/Eintracht_hooligans.jpg/200px-Eintracht_hooligans.jpg","url":"https://upload.wikimedia.org/wikipedia/commons/6/6c/Eintracht_hooligans.jpg","badImage":false},{"name":"Sociologielogo.png#WIKIDATA","languages":["FR"],"urlSource":"WIKIDATA","license":"CC_BY_SA_30","thumbUrl":"https://upload.wikimedia.org/wikipedia/commons/thumb/9/9c/Sociologielogo.png/200px-Sociologielogo.png","url":"https://upload.wikimedia.org/wikipedia/commons/9/9c/Sociologielogo.png","badImage":false}],"categories":[{"category":"Criminology","language":"EN"},{"category":"Deviance_and_social_control","language":"EN"},{"category":"Deviance_(sociology)","language":"EN"},{"category":"Stereotypes","language":"EN"}],"synsetType":"CONCEPT","translations":{},"targetLangs":["KO","EN"]}]