[{"id":{"id":"bn:00000613n","pos":"NOUN","source":"BABELNET"},"bKeyConcept":false,"bLoaded":true,"senses":[{"fullLemma":"acariasis","simpleLemma":"acariasis","source":"WNTR","senseKey":"","frequency":0,"language":"KO","pos":"NOUN","synsetID":{"id":"bn:00000613n","pos":"NOUN","source":"BABELNET"},"translationInfo":"1.0_0_0","pronunciations":{"audios":[],"transcriptions":[]},"bKeySense":false,"idSense":46579300},{"fullLemma":"acaridiasis","simpleLemma":"acaridiasis","source":"WNTR","senseKey":"","frequency":0,"language":"KO","pos":"NOUN","synsetID":{"id":"bn:00000613n","pos":"NOUN","source":"BABELNET"},"translationInfo":"1.0_0_0","pronunciations":{"audios":[],"transcriptions":[]},"bKeySense":false,"idSense":46579372},{"fullLemma":"acariosis","simpleLemma":"acariosis","source":"WNTR","senseKey":"","frequency":0,"language":"KO","pos":"NOUN","synsetID":{"id":"bn:00000613n","pos":"NOUN","source":"BABELNET"},"translationInfo":"1.0_0_0","pronunciations":{"audios":[],"transcriptions":[]},"bKeySense":false,"idSense":46579355}],"domains":{"HEALTH_AND_MEDICINE":0.4173099994659424},"lnToCompound":{},"lnToOtherForm":{},"wnOffsets":[{"versionMapping":{"1.6":["10369786n"],"3.0":["14453066n"],"2.1":["14261333n"],"2.0":["13633072n"],"1.7":["12205400n"]},"version":"WN_30","id":"wn:14453066n","pos":"NOUN","source":"WN"}],"mainSenses":{},"glosses":[{"source":"WN","sourceSense":"46579275","language":"EN","gloss":"Infestation with itch mites","tokens":[{"start":0,"end":10,"id":{"id":"bn:00046657n","pos":"NOUN","source":"BABELNET"},"word":"Infestation"},{"start":22,"end":26,"id":{"id":"bn:00055357n","pos":"NOUN","source":"BABELNET"},"word":"mites"},{"start":17,"end":20,"id":{"id":"bn:00047727n","pos":"NOUN","source":"BABELNET"},"word":"itch"},{"start":17,"end":26,"id":{"id":"bn:00047728n","pos":"NOUN","source":"BABELNET"},"word":"itch mites"}]},{"source":"WIKI","sourceSense":"46579412","language":"EN","gloss":"Acariasis is an infestation with mites.","tokens":[{"start":16,"end":26,"id":{"id":"bn:00046657n","pos":"NOUN","source":"BABELNET"},"word":"infestation"},{"start":33,"end":37,"id":{"id":"bn:00055357n","pos":"NOUN","source":"BABELNET"},"word":"mites"}]},{"source":"WIKT","sourceSense":"46579445","language":"EN","gloss":"An infestation with, or disease caused by mites or ticks.","tokens":[{"start":42,"end":46,"id":{"id":"bn:00055357n","pos":"NOUN","source":"BABELNET"},"word":"mites"},{"start":3,"end":13,"id":{"id":"bn:00046657n","pos":"NOUN","source":"BABELNET"},"word":"infestation"},{"start":51,"end":55,"id":{"id":"bn:00077170n","pos":"NOUN","source":"BABELNET"},"word":"ticks"}]},{"source":"WIKT","sourceSense":"46579446","language":"EN","gloss":"Acariasis.","tokens":[]}],"examples":[],"images":[{"name":"ScabiesD08.JPG#OMWIKI","languages":["RU"],"urlSource":"OMWIKI","license":"CC_BY_30","thumbUrl":"https://upload.wikimedia.org/wikipedia/commons/thumb/2/23/ScabiesD08.JPG/200px-ScabiesD08.JPG","url":"https://upload.wikimedia.org/wikipedia/commons/2/23/ScabiesD08.JPG","badImage":false},{"name":"Sarcoptes_scabei_2.jpg#WIKI","languages":["RU","IT"],"urlSource":"WIKI","license":"CC_BY_SA_30","thumbUrl":"https://upload.wikimedia.org/wikipedia/commons/thumb/c/c0/Sarcoptes_scabei_2.jpg/200px-Sarcoptes_scabei_2.jpg","url":"https://upload.wikimedia.org/wikipedia/commons/c/c0/Sarcoptes_scabei_2.jpg","badImage":false},{"name":"Demodectic_mange_2.jpg#WIKI","languages":["RO","NL"],"urlSource":"WIKI","license":"CC_BY_SA_30","thumbUrl":"https://upload.wikimedia.org/wikipedia/commons/thumb/5/5d/Demodectic_mange_2.jpg/200px-Demodectic_mange_2.jpg","url":"https://upload.wikimedia.org/wikipedia/commons/5/5d/Demodectic_mange_2.jpg","badImage":false},{"name":"ScabiesD08.JPG#WIKI","languages":["RU"],"urlSource":"WIKI","license":"CC_BY_SA_30","thumbUrl":"https://upload.wikimedia.org/wikipedia/commons/thumb/2/23/ScabiesD08.JPG/200px-ScabiesD08.JPG","url":"https://upload.wikimedia.org/wikipedia/commons/2/23/ScabiesD08.JPG","badImage":false},{"name":"Haarbalgmilbe.jpg#WIKI","languages":["RO"],"urlSource":"WIKI","license":"CC_BY_SA_30","thumbUrl":"https://upload.wikimedia.org/wikipedia/commons/thumb/0/0e/Haarbalgmilbe.jpg/200px-Haarbalgmilbe.jpg","url":"https://upload.wikimedia.org/wikipedia/commons/0/0e/Haarbalgmilbe.jpg","badImage":false},{"name":"Tracheal_mite_-_Acarapis_woodi.jpg#WIKI","languages":["RO"],"urlSource":"WIKI","license":"CC_BY_SA_30","thumbUrl":"https://upload.wikimedia.org/wikipedia/commons/thumb/8/83/Tracheal_mite_-_Acarapis_woodi.jpg/200px-Tracheal_mite_-_Acarapis_woodi.jpg","url":"https://upload.wikimedia.org/wikipedia/commons/8/83/Tracheal_mite_-_Acarapis_woodi.jpg","badImage":false},{"name":"Taenia_emplumada.jpg#WIKI","languages":["FR"],"urlSource":"WIKI","license":"CC_BY_SA_30","thumbUrl":"https://upload.wikimedia.org/wikipedia/commons/thumb/4/4a/Taenia_emplumada.jpg/200px-Taenia_emplumada.jpg","url":"https://upload.wikimedia.org/wikipedia/commons/4/4a/Taenia_emplumada.jpg","badImage":false}],"categories":[{"category":"Arthropod_infestations","language":"EN"}],"synsetType":"CONCEPT","translations":{},"targetLangs":["KO","EN"]}]