[{"id":{"id":"bn:00000799n","pos":"NOUN","source":"BABELNET"},"bKeyConcept":false,"bLoaded":true,"senses":[{"fullLemma":"아세부톨롤","simpleLemma":"아세부톨롤","source":"WIKI","senseKey":"712666","frequency":0,"language":"KO","pos":"NOUN","synsetID":{"id":"bn:00000799n","pos":"NOUN","source":"BABELNET"},"translationInfo":"","pronunciations":{"audios":[],"transcriptions":[]},"bKeySense":false,"idSense":46615806},{"fullLemma":"아세부톨롤","simpleLemma":"아세부톨롤","source":"WIKIDATA","senseKey":"Q418857","frequency":0,"language":"KO","pos":"NOUN","synsetID":{"id":"bn:00000799n","pos":"NOUN","source":"BABELNET"},"translationInfo":"","pronunciations":{"audios":[],"transcriptions":[]},"bKeySense":false,"idSense":228357409},{"fullLemma":"acebutolol","simpleLemma":"acebutolol","source":"WIKITR","senseKey":"","frequency":0,"language":"KO","pos":"NOUN","synsetID":{"id":"bn:00000799n","pos":"NOUN","source":"BABELNET"},"translationInfo":"0.60000_3_5","pronunciations":{"audios":[],"transcriptions":[]},"bKeySense":false,"idSense":46615870},{"fullLemma":"acebutolol","simpleLemma":"acebutolol","source":"WNTR","senseKey":"","frequency":0,"language":"KO","pos":"NOUN","synsetID":{"id":"bn:00000799n","pos":"NOUN","source":"BABELNET"},"translationInfo":"1.0_0_0","pronunciations":{"audios":[],"transcriptions":[]},"bKeySense":false,"idSense":46615794},{"fullLemma":"sectral","simpleLemma":"sectral","source":"WNTR","senseKey":"","frequency":0,"language":"KO","pos":"NOUN","synsetID":{"id":"bn:00000799n","pos":"NOUN","source":"BABELNET"},"translationInfo":"1.0_0_0","pronunciations":{"audios":[],"transcriptions":[]},"bKeySense":false,"idSense":46615727}],"domains":{"HEALTH_AND_MEDICINE":0.36692681908607483},"lnToCompound":{},"lnToOtherForm":{},"wnOffsets":[{"versionMapping":{"1.6":["02161132n"],"3.0":["02673480n"],"2.1":["02648949n"],"2.0":["02581659n"],"1.7":["02325947n"]},"version":"WN_30","id":"wn:02673480n","pos":"NOUN","source":"WN"}],"mainSenses":{},"glosses":[{"source":"WN","sourceSense":"46615706","language":"EN","gloss":"An oral beta blocker (trade name Sectral) used in treating hypertension","tokens":[{"start":22,"end":31,"id":{"id":"bn:00012758n","pos":"NOUN","source":"BABELNET"},"word":"trade name"},{"start":50,"end":57,"id":{"id":"bn:00084532v","pos":"VERB","source":"BABELNET"},"word":"treating"},{"start":8,"end":19,"id":{"id":"bn:00010115n","pos":"NOUN","source":"BABELNET"},"word":"beta blocker"},{"start":59,"end":70,"id":{"id":"bn:00044056n","pos":"NOUN","source":"BABELNET"},"word":"hypertension"}]},{"source":"WIKI","sourceSense":"46615805","language":"EN","gloss":"Acebutolol is a beta blocker for the treatment of hypertension and arrhythmias.","tokens":[{"start":16,"end":27,"id":{"id":"bn:00010115n","pos":"NOUN","source":"BABELNET"},"word":"beta blocker"},{"start":37,"end":61,"id":{"id":"bn:00004678n","pos":"NOUN","source":"BABELNET"},"word":"treatment of hypertension"},{"start":67,"end":77,"id":{"id":"bn:00005883n","pos":"NOUN","source":"BABELNET"},"word":"arrhythmias"}]},{"source":"WIKIDATA","sourceSense":"252048879","language":"EN","gloss":"Pharmaceutical drug","tokens":[]},{"source":"WIKT","sourceSense":"46615896","language":"EN","gloss":"A particular beta blocker used in the treatment of hypertension and arrhythmias.","tokens":[]},{"source":"WIKI","sourceSense":"46615806","language":"KO","gloss":"아세부톨롤은 베타1-선택성 아드레날린 수용체 길항제이다.","tokens":[]}],"examples":[],"images":[{"name":"Acebutolol_structure.svg#WIKI","languages":["SR","UK","AR","PL","KO","DE","LV","SH","FR","EN"],"urlSource":"WIKI","license":"CC_BY_SA_30","thumbUrl":"https://upload.wikimedia.org/wikipedia/commons/4/47/Acebutolol_structure.svg","url":"https://upload.wikimedia.org/wikipedia/commons/4/47/Acebutolol_structure.svg","badImage":false},{"name":"Acebutolol.svg#WIKI","languages":["ES","IT"],"urlSource":"WIKI","license":"CC_BY_SA_30","thumbUrl":"https://upload.wikimedia.org/wikipedia/commons/c/cf/Acebutolol.svg","url":"https://upload.wikimedia.org/wikipedia/commons/c/cf/Acebutolol.svg","badImage":false},{"name":"Acebutolol_ball-and-stick.png#WIKI","languages":["EN"],"urlSource":"WIKI","license":"CC_BY_SA_30","thumbUrl":"https://upload.wikimedia.org/wikipedia/commons/thumb/6/60/Acebutolol_ball-and-stick.png/200px-Acebutolol_ball-and-stick.png","url":"https://upload.wikimedia.org/wikipedia/commons/6/60/Acebutolol_ball-and-stick.png","badImage":false},{"name":"Acebutolol_synthesis_01.svg#WIKI","languages":["DE"],"urlSource":"WIKI","license":"CC_BY_SA_30","thumbUrl":"https://upload.wikimedia.org/wikipedia/commons/1/1c/Acebutolol_synthesis_01.svg","url":"https://upload.wikimedia.org/wikipedia/commons/1/1c/Acebutolol_synthesis_01.svg","badImage":false},{"name":"Acebutolol_3d-model-bonds.png#WIKI","languages":["PL"],"urlSource":"WIKI","license":"CC_BY_SA_30","thumbUrl":"https://upload.wikimedia.org/wikipedia/commons/thumb/9/92/Acebutolol_3d-model-bonds.png/200px-Acebutolol_3d-model-bonds.png","url":"https://upload.wikimedia.org/wikipedia/commons/9/92/Acebutolol_3d-model-bonds.png","badImage":false},{"name":"Lisdexamfetamine_caps.jpg#WIKI","languages":["PT"],"urlSource":"WIKI","license":"CC_BY_SA_30","thumbUrl":"https://upload.wikimedia.org/wikipedia/commons/thumb/4/4d/Lisdexamfetamine_caps.jpg/200px-Lisdexamfetamine_caps.jpg","url":"https://upload.wikimedia.org/wikipedia/commons/4/4d/Lisdexamfetamine_caps.jpg","badImage":false},{"name":"Medicine_Drugs.svg#WIKI","languages":["UK"],"urlSource":"WIKI","license":"CC_BY_SA_30","thumbUrl":"https://upload.wikimedia.org/wikipedia/commons/7/76/Medicine_Drugs.svg","url":"https://upload.wikimedia.org/wikipedia/commons/7/76/Medicine_Drugs.svg","badImage":false},{"name":"Yes_Check_Circle.svg#WIKI","languages":["AR"],"urlSource":"WIKI","license":"CC_BY_SA_30","thumbUrl":"https://upload.wikimedia.org/wikipedia/commons/5/50/Yes_Check_Circle.svg","url":"https://upload.wikimedia.org/wikipedia/commons/5/50/Yes_Check_Circle.svg","badImage":false},{"name":"P_Pharmaceutics.svg#WIKI","languages":["AR"],"urlSource":"WIKI","license":"CC_BY_SA_30","thumbUrl":"https://upload.wikimedia.org/wikipedia/commons/2/2a/P_Pharmaceutics.svg","url":"https://upload.wikimedia.org/wikipedia/commons/2/2a/P_Pharmaceutics.svg","badImage":false},{"name":"Crystal_Clear_app_virussafe.png#WIKI","languages":["LV"],"urlSource":"WIKI","license":"CC_BY_SA_30","thumbUrl":"https://upload.wikimedia.org/wikipedia/commons/3/37/Crystal_Clear_app_virussafe.png","url":"https://upload.wikimedia.org/wikipedia/commons/3/37/Crystal_Clear_app_virussafe.png","badImage":false},{"name":"Bowl_Of_Hygieia_by_David.svg#WIKI","languages":["PT"],"urlSource":"WIKI","license":"CC_BY_SA_30","thumbUrl":"https://upload.wikimedia.org/wikipedia/commons/7/7b/Bowl_Of_Hygieia_by_David.svg","url":"https://upload.wikimedia.org/wikipedia/commons/7/7b/Bowl_Of_Hygieia_by_David.svg","badImage":false},{"name":"SinusRhythmLabels.svg#WIKI","languages":["IT"],"urlSource":"WIKI","license":"CC_BY_SA_30","thumbUrl":"https://upload.wikimedia.org/wikipedia/commons/9/9e/SinusRhythmLabels.svg","url":"https://upload.wikimedia.org/wikipedia/commons/9/9e/SinusRhythmLabels.svg","badImage":false}],"categories":[{"category":"베타_차단제","language":"KO"},{"category":"아닐라이드","language":"KO"},{"category":"Alcohols","language":"EN"},{"category":"Anilides","language":"EN"},{"category":"Aromatic_ketones","language":"EN"},{"category":"Beta_blockers","language":"EN"},{"category":"Phenol_ethers","language":"EN"}],"synsetType":"CONCEPT","translations":{},"targetLangs":["KO","EN"]}]